[
  {
    "url": "assets/images/macromedia-2/01.jpg",
    "scenes": [
      {
        "translateX": 0,
        "translateY": -5,
        "translateZ": 0
      },
      {
        "translateX": 0,
        "translateY": 30,
        "translateZ": 500
      },
      {
        "translateX": 0,
        "translateY": -30,
        "translateZ": 550
      }
    ]
  },
  {
    "url": "assets/images/macromedia-2/02.jpg",
    "scenes": [
      {
        "translateX": 0,
        "translateY": 35,
        "translateZ": 675
      },
      {
        "translateX": 0,
        "translateY": 12,
        "translateZ": 713
      },
      {
        "translateX": 0,
        "translateY": -8,
        "translateZ": 715
      },
      {
        "translateX": 0,
        "translateY": -32,
        "translateZ": 670
      }
    ]
  },
  {
    "url": "assets/images/macromedia-2/03.jpg",
    "scenes": [
      {
        "translateX": 0,
        "translateY": 37,
        "translateZ": 725
      },
      {
        "translateX": 0,
        "translateY": 18,
        "translateZ": 715
      },
      {
        "translateX": 0,
        "translateY": -5,
        "translateZ": 715
      },
      {
        "translateX": 0,
        "translateY": -32,
        "translateZ": 675
      }
    ]
  },
  {
    "url": "assets/images/macromedia-2/04.jpg",
    "scenes": [
      {
        "translateX": 19,
        "translateY": 37,
        "translateZ": 775
      },
      {
        "translateX": 19,
        "translateY": 20,
        "translateZ": 730
      },
      {
        "translateX": -20,
        "translateY": 26,
        "translateZ": 753
      },
      {
        "translateX": 23,
        "translateY": -5,
        "translateZ": 700
      },
      {
        "translateX": -41,
        "translateY": 1,
        "translateZ": 711
      },
      {
        "translateX": -3,
        "translateY": -29,
        "translateZ": 660
      }
    ]
  },
  {
    "url": "assets/images/macromedia-2/05.jpg",
    "scenes": [
      {
        "translateX": 0,
        "translateY": 30,
        "translateZ": 680
      },
      {
        "translateX": 0,
        "translateY": 1,
        "translateZ": 650
      },
      {
        "translateX": 0,
        "translateY": -31,
        "translateZ": 650
      }
    ]
  },
  {
    "url": "assets/images/macromedia-2/06-07.jpg",
    "scenes": [
      {
        "translateX": 0,
        "translateY": 0,
        "translateZ": 500
      },
      {
        "translateX": 0,
        "translateY": 32,
        "translateZ": 700
      },
      {
        "translateX": 27,
        "translateY": 32,
        "translateZ": 900
      },
      {
        "translateX": -23,
        "translateY": 31,
        "translateZ": 850
      },
      {
        "translateX": 19,
        "translateY": 1,
        "translateZ": 818
      },
      {
        "translateX": -19,
        "translateY": 1,
        "translateZ": 820
      },
      {
        "translateX": 18,
        "translateY": -28,
        "translateZ": 820
      },
      {
        "translateX": -19,
        "translateY": -28,
        "translateZ": 820
      }
    ]
  },
  {
    "url": "assets/images/macromedia-2/08.jpg",
    "scenes": [
      {
        "translateX": 0,
        "translateY": 0,
        "translateZ": 500
      },
      {
        "translateX": 0,
        "translateY": 32,
        "translateZ": 700
      },
      {
        "translateX": 27,
        "translateY": 32,
        "translateZ": 900
      },
      {
        "translateX": -23,
        "translateY": 31,
        "translateZ": 850
      },
      {
        "translateX": 19,
        "translateY": 1,
        "translateZ": 818
      },
      {
        "translateX": -19,
        "translateY": 1,
        "translateZ": 820
      },
      {
        "translateX": 18,
        "translateY": -28,
        "translateZ": 820
      },
      {
        "translateX": -19,
        "translateY": -28,
        "translateZ": 820
      }
    ]
  },
  {
    "url": "assets/images/macromedia-2/09.jpg",
    "scenes": [
      {
        "translateX": 0,
        "translateY": 36,
        "translateZ": 715
      },
      {
        "translateX": 0,
        "translateY": 8,
        "translateZ": 650
      },
      {
        "translateX": 0,
        "translateY": -17,
        "translateZ": 714
      },
      {
        "translateX": 2,
        "translateY": -36,
        "translateZ": 750
      }
    ]
  },
  {
    "url": "assets/images/macromedia-2/10.jpg",
    "scenes": [
      {
        "translateX": 0,
        "translateY": 27,
        "translateZ": 650
      },
      {
        "translateX": 0,
        "translateY": -3,
        "translateZ": 675
      },
      {
        "translateX": 0,
        "translateY": -33,
        "translateZ": 675
      }
    ]
  },
  {
    "url": "assets/images/macromedia-2/11.jpg",
    "scenes": [
      {
        "translateX": 0,
        "translateY": 36,
        "translateZ": 715
      },
      {
        "translateX": 0,
        "translateY": 12,
        "translateZ": 670
      },
      {
        "translateX": 0,
        "translateY": -13,
        "translateZ": 710
      },
      {
        "translateX": 0,
        "translateY": -34,
        "translateZ": 724
      }
    ]
  },
  {
    "url": "assets/images/macromedia-2/12.jpg",
    "scenes": [
      {
        "translateX": 0,
        "translateY": 34,
        "translateZ": 750
      },
      {
        "translateX": 0,
        "translateY": 15,
        "translateZ": 720
      },
      {
        "translateX": 0,
        "translateY": -3,
        "translateZ": 730
      },
      {
        "translateX": 0,
        "translateY": -20,
        "translateZ": 730
      },
      {
        "translateX": 0,
        "translateY": -35,
        "translateZ": 725
      }
    ]
  },
  {
    "url": "assets/images/macromedia-2/13.jpg",
    "scenes": [
      {
        "translateX": 0,
        "translateY": 33,
        "translateZ": 715
      },
      {
        "translateX": 0,
        "translateY": 12,
        "translateZ": 715
      },
      {
        "translateX": 0,
        "translateY": -11,
        "translateZ": 715
      },
      {
        "translateX": 0,
        "translateY": -34,
        "translateZ": 680
      }
    ]
  },
  {
    "url": "assets/images/macromedia-2/14.jpg",
    "scenes": [
      {
        "translateX": 0,
        "translateY": 31,
        "translateZ": 710
      },
      {
        "translateX": 0,
        "translateY": 8,
        "translateZ": 720
      },
      {
        "translateX": 0,
        "translateY": -12,
        "translateZ": 720
      },
      {
        "translateX": 0,
        "translateY": -34,
        "translateZ": 720
      }
    ]
  },
  {
    "url": "assets/images/macromedia-2/15.jpg",
    "scenes": [
      {
        "translateX": 0,
        "translateY": 26,
        "translateZ": 622
      },
      {
        "translateX": 0,
        "translateY": -4,
        "translateZ": 700
      },
      {
        "translateX": 0,
        "translateY": -31,
        "translateZ": 671
      }
    ]
  },
  {
    "url": "assets/images/macromedia-2/16.jpg",
    "scenes": [
      {
        "translateX": 0,
        "translateY": -6,
        "translateZ": 0
      },
      {
        "translateX": 0,
        "translateY": 6,
        "translateZ": 630
      },
      {
        "translateX": 16,
        "translateY": -30,
        "translateZ": 850
      }
    ]
  }
]